colander/__init__.py
colander/compat.py
colander/interfaces.py
colander/locale/colander.pot
colander/locale/cs/LC_MESSAGES/colander.mo
colander/locale/cs/LC_MESSAGES/colander.po
colander/locale/de/LC_MESSAGES/colander.mo
colander/locale/de/LC_MESSAGES/colander.po
colander/locale/el/LC_MESSAGES/colander.mo
colander/locale/el/LC_MESSAGES/colander.po
colander/locale/es/LC_MESSAGES/colander.mo
colander/locale/es/LC_MESSAGES/colander.po
colander/locale/fi/LC_MESSAGES/colander.mo
colander/locale/fi/LC_MESSAGES/colander.po
colander/locale/fr/LC_MESSAGES/colander.mo
colander/locale/fr/LC_MESSAGES/colander.po
colander/locale/it/LC_MESSAGES/colander.mo
colander/locale/it/LC_MESSAGES/colander.po
colander/locale/ja/LC_MESSAGES/colander.mo
colander/locale/ja/LC_MESSAGES/colander.po
colander/locale/nl/LC_MESSAGES/colander.mo
colander/locale/nl/LC_MESSAGES/colander.po
colander/locale/pl/LC_MESSAGES/colander.mo
colander/locale/pl/LC_MESSAGES/colander.po
colander/locale/pt/LC_MESSAGES/colander.mo
colander/locale/pt/LC_MESSAGES/colander.po
colander/locale/pt_BR/LC_MESSAGES/colander.mo
colander/locale/pt_BR/LC_MESSAGES/colander.po
colander/locale/ro/LC_MESSAGES/colander.mo
colander/locale/ro/LC_MESSAGES/colander.po
colander/locale/ru/LC_MESSAGES/colander.mo
colander/locale/ru/LC_MESSAGES/colander.po
colander/locale/sv/LC_MESSAGES/colander.mo
colander/locale/sv/LC_MESSAGES/colander.po
colander/locale/zh_Hans/LC_MESSAGES/colander.mo
colander/locale/zh_Hans/LC_MESSAGES/colander.po
colander/locale/zh_Hant/LC_MESSAGES/colander.mo
colander/locale/zh_Hant/LC_MESSAGES/colander.po
colander-1.8.2.dist-info/LICENSE.txt
colander-1.8.2.dist-info/METADATA
colander-1.8.2.dist-info/WHEEL
colander-1.8.2.dist-info/top_level.txt
colander-1.8.2.dist-info/RECORD
