Metadata-Version: 2.1
Name: colander
Version: 1.8.2
Summary: A simple schema-based serialization and deserialization library
Home-page: https://github.com/Pylons/colander
Author: Agendaless Consulting
Author-email: pylons-discuss@googlegroups.com
Maintainer: Pylons Project
Maintainer-email: pylons-discuss@googlegroups.com
License: BSD-derived (http://www.repoze.org/LICENSE.txt)
Project-URL: Documentation, https://docs.pylonsproject.org/projects/colander/en/latest/index.html
Project-URL: Changelog, https://docs.pylonsproject.org/projects/colander/en/latest/changes.html
Project-URL: Issue Tracker, https://github.com/Pylons/colander/issues
Keywords: serialize deserialize validate schema validation
Platform: UNKNOWN
Classifier: Development Status :: 6 - Mature
Classifier: Intended Audience :: Developers
Classifier: Programming Language :: Python
Classifier: Programming Language :: Python :: 2
Classifier: Programming Language :: Python :: 2.7
Classifier: Programming Language :: Python :: 3
Classifier: Programming Language :: Python :: 3.5
Classifier: Programming Language :: Python :: 3.6
Classifier: Programming Language :: Python :: 3.7
Classifier: Programming Language :: Python :: 3.8
Classifier: Programming Language :: Python :: Implementation :: CPython
Classifier: Programming Language :: Python :: Implementation :: PyPy
Classifier: Operating System :: OS Independent
Classifier: License :: Repoze Public License
Requires-Python: !=3.0.*,!=3.1.*,!=3.2.*,!=3.3.*,!=3.4.*,>=2.7
Requires-Dist: translationstring
Requires-Dist: iso8601
Requires-Dist: setuptools (>=11.3)
Requires-Dist: enum34 ; python_version in "2.7"
Provides-Extra: docs
Requires-Dist: Sphinx (>=1.8.1) ; extra == 'docs'
Requires-Dist: docutils ; extra == 'docs'
Requires-Dist: pylons-sphinx-themes (>=1.0.9) ; extra == 'docs'
Provides-Extra: testing
Requires-Dist: pytest ; extra == 'testing'
Requires-Dist: pytest-cov ; extra == 'testing'
Requires-Dist: coverage (>=5.0) ; extra == 'testing'
